nav_requests/__init__.py
nav_requests-1.1.4.dist-info/DESCRIPTION.rst
nav_requests-1.1.4.dist-info/METADATA
nav_requests-1.1.4.dist-info/RECORD
nav_requests-1.1.4.dist-info/WHEEL
nav_requests-1.1.4.dist-info/entry_points.txt
nav_requests-1.1.4.dist-info/metadata.json
nav_requests-1.1.4.dist-info/top_level.txt
