Metadata-Version: 2.0
Name: nav-requests
Version: 1.1.4
Summary: Renamed to `nav`
Home-page: https://pypi.python.org/pypi/nav
Author: Jacob Magnusson
Author-email: m@jacobian.se
License: BSD
Platform: any
Classifier: Development Status :: 5 - Production/Stable
Classifier: Environment :: Web Environment
Classifier: Intended Audience :: Developers
Classifier: License :: OSI Approved :: BSD License
Classifier: Operating System :: OS Independent
Classifier: Programming Language :: Python
Classifier: Programming Language :: Python :: 3.5
Requires-Dist: argh
Requires-Dist: lxml
Requires-Dist: requests
Requires-Dist: requests-ntlm
Requires-Dist: xmltodict
Provides-Extra: test
Requires-Dist: pytest (>=3.0.3); extra == 'test'
Requires-Dist: coverage (>=4.2); extra == 'test'
Requires-Dist: flake8 (>=3.0.4); extra == 'test'
